contils/__init__.py
contils/color.py
contils/flash.py
contils/raw.py
contils/table.py
contils-0.1.0.dist-info/METADATA
contils-0.1.0.dist-info/RECORD
contils-0.1.0.dist-info/WHEEL
contils-0.1.0.dist-info/top_level.txt
