Metadata-Version: 2.1
Name: contils
Version: 0.1.0
Summary: Console utilities
Home-page: https://github.com/4Bos/contils
Author: Konstantin Veselovsky
Author-email: kos@scompiler.ru
License: UNKNOWN
Platform: UNKNOWN
